<?xml version="1.0" encoding="UTF-8"?>
<con:soapui-project id="6d21b696-49c3-41f8-b019-3e763becfd7c" activeEnvironment="Default" name="REST Project 2" resourceRoot="" soapui-version="5.4.0" xmlns:con="http://eviware.com/soapui/config"><con:settings/><con:interface xsi:type="con:RestService" id="d9de3621-16a3-4b17-8791-727d2e96c938" wadlVersion="http://wadl.dev.java.net/2009/02" name="http://maps.googleapis.com" type="rest" xmlns:xsi="http://www.w3.org/2001/XMLSchema-instance"><con:settings/><con:definitionCache type="TEXT" rootPart=""/><con:endpoints><con:endpoint>http://maps.googleapis.com</con:endpoint></con:endpoints><con:resource name="Xml" path="/maps/api/geocode/json" id="db21475c-da52-4244-b4a6-15da6b096820"><con:settings/><con:parameters><con:parameter><con:name>address</con:name><con:value>1600 Amphitheatre Parkway, Mountain View, CA</con:value><con:style>QUERY</con:style><con:default>1600 Amphitheatre Parkway, Mountain View, CA</con:default><con:path xsi:nil="true"/><con:description xsi:nil="true"/></con:parameter><con:parameter><con:name>sensor</con:name><con:value>false</con:value><con:style>QUERY</con:style><con:default>false</con:default><con:path xsi:nil="true"/><con:description xsi:nil="true"/></con:parameter></con:parameters><con:method name="Xml 1" id="6a3b236a-3386-4d6d-9da2-4b9a3e790377" method="GET"><con:settings/><con:parameters/><con:representation type="RESPONSE"><con:mediaType>application/xml; charset=UTF-8</con:mediaType><con:status>200</con:status><con:params/><con:element>GeocodeResponse</con:element></con:representation><con:representation type="RESPONSE"><con:mediaType>application/json; charset=UTF-8</con:mediaType><con:status>200</con:status><con:params/><con:element xmlns:ns="http://maps.googleapis.com/maps/api/geocode/xml">ns:Response</con:element></con:representation><con:request name="Request 1" id="076d65c1-02d6-49dc-ab85-a0e268532283" mediaType="application/json"><con:settings><con:setting id="com.eviware.soapui.impl.wsdl.WsdlRequest@request-headers">&lt;xml-fragment/></con:setting></con:settings><con:endpoint>http://maps.googleapis.com</con:endpoint><con:request/><con:originalUri>http://maps.googleapis.com/maps/api/geocode/xml</con:originalUri><con:credentials><con:authType>No Authorization</con:authType></con:credentials><con:jmsConfig JMSDeliveryMode="PERSISTENT"/><con:jmsPropertyConfig/><con:parameters>
  <con:entry key="address" value="1600 Amphitheatre Parkway, Mountain View, CA"/>
  <con:entry key="sensor" value="false"/>
</con:parameters><con:parameterOrder><con:entry>address</con:entry><con:entry>sensor</con:entry></con:parameterOrder></con:request></con:method></con:resource></con:interface><con:testSuite id="52f955fd-d94d-44bf-a824-697242b8adc1" name="TestSuite 1"><con:settings/><con:runType>SEQUENTIAL</con:runType><con:testCase id="2c16239f-f038-4e03-a344-9956286fb70a" failOnError="true" failTestCaseOnErrors="true" keepSession="false" maxResults="0" name="Get places - Request 1" searchProperties="true"><con:settings/><con:testStep type="restrequest" name="Xml 1 - Request 1" id="923d3c72-2a24-4c35-95f8-51d0078c51b6"><con:settings/><con:config service="http://maps.googleapis.com" resourcePath="/maps/api/geocode/json" methodName="Xml 1" xsi:type="con:RestRequestStep" xmlns:xsi="http://www.w3.org/2001/XMLSchema-instance"><con:restRequest name="Xml 1 - Request 1" id="076d65c1-02d6-49dc-ab85-a0e268532283" mediaType="application/json"><con:settings><con:setting id="com.eviware.soapui.impl.wsdl.WsdlRequest@request-headers">&lt;xml-fragment/></con:setting></con:settings><con:endpoint>http://maps.googleapis.com</con:endpoint><con:request/><con:originalUri>http://maps.googleapis.com/maps/api/geocode/xml</con:originalUri><con:credentials><con:authType>No Authorization</con:authType></con:credentials><con:jmsConfig JMSDeliveryMode="PERSISTENT"/><con:jmsPropertyConfig/><con:parameters>
  <con:entry key="address" value="1600 Amphitheatre Parkway, Mountain View, CA"/>
  <con:entry key="sensor" value="false"/>
</con:parameters><con:parameterOrder><con:entry>address</con:entry><con:entry>sensor</con:entry></con:parameterOrder></con:restRequest></con:config></con:testStep><con:properties/></con:testCase><con:properties/></con:testSuite><con:properties/><con:wssContainer/><con:oAuth2ProfileContainer/><con:oAuth1ProfileContainer/></con:soapui-project>